{"state":"In uitvoering","startDateTime":"2017-08-31T07:00:00","endDateTime":"2019-11-26T19:00:00","type":"Andere","contractor":null,"mainContractor":null,"gipodId":1002010,"owner":"De Vlaamse Waterweg nv","reference":"Bouw brug Herentals-Lier - 43","description":"Bouw van nieuwe brug","comment":null,"location":{"cities":["Herentals"],"coordinate":{"coordinates":[4.8124438805873648,51.173642678009074],"type":"Point","crs":{"type":"name","properties":{"name":"urn:ogc:def:crs:OGC:1.3:CRS84"}}},"geometry":{"coordinates":[[[4.811140869497768,51.1733277248346],[4.8121696258424791,51.173622735852312],[4.8124988984576431,51.173664193720938],[4.8126631175970918,51.173641103919131],[4.8133019315356282,51.173903864576687],[4.8136888225502465,51.173614766811724],[4.8132025614001748,51.1732300857844],[4.81341831791193,51.172988824395787],[4.8144068118566485,51.172810936739985],[4.8135318298451466,51.171398517208338],[4.8118774525649144,51.171467666387883],[4.8107341346483121,51.171525889334461],[4.8102200919163929,51.171599724552777],[4.8101338469086814,51.171551733042122],[4.8099090911347568,51.17159864122759],[4.8098456437990693,51.171693260073724],[4.8094920248527986,51.171721548373014],[4.808996062734205,51.171817782451996],[4.809157739609403,51.172093581708246],[4.8097089284707968,51.1719780394599],[4.8099068654049271,51.172496397344467],[4.8103132185310109,51.173128580689138],[4.811140869497768,51.1733277248346]]],"type":"Polygon","crs":{"type":"name","properties":{"name":"urn:ogc:def:crs:OGC:1.3:CRS84"}}}},"url":null,"latestUpdate":"2017-10-12T11:08:31.737","hindrance":{"direction":"Beide","description":"Bouw van een nieuwe brug 43:\r\n\r\nDe bestaande brug wordt afgebroken en vervangen door een nieuwe boogbrug. De nieuwe brug zal op dezelfde locatie als de bestaande brug komen te liggen. Ten oosten van de bestaande brug zal eerst de nieuwe brug worden geplaatst op een tijdelijke locatie, terwijl het verkeer nog gebruik kan maken van de bestaande brug. Na voltooiing wordt de nieuwe brug op haar tijdelijke locatie in gebruik genomen, waarna de bestaande brug kan worden afgebroken. Daarna wordt de nieuwe brug op de locatie van de huidige ingevaren.\r\nTijdens de uitvoering van de werken blijft het bestaande wegennet volledig beschikbaar met uitzondering van de tijdelijk te onderbreken N13-Lierseweg en de jaagpaden. \r\n\r\nConcreet wordt het wegverkeer over de brug (N13-Lierseweg) onderbroken van 17/06/2019 t.e.m. 24/07/2019. Dit brengt de onderstaand opgesomde hinder met zich mee.\r\n\r\nBijkomend wordt het jaagpad linkeroever onderbroken van 01/12/2018 t.e.m. 26/11/2019.\r\nJaagpad rechteroever wordt onderbroken van 14/05/2018 t.e.m. 18/05/2018, van 25/06/2018 t.e.m. 29/06/2018, van 18/01/2019 t.e.m. 15/02/2019 en van 17/06/2019 t.e.m. 22/06/2019.\r\n  ","locations":["Voetpad","Fietspad","Zijberm","Rijbaan","Halte openbaar vervoer"],"important":true,"effects":["Omleiding: beide richtingen","Afgesloten: volledige rijweg","Afgesloten: brug","Fietsers hebben geen doorgang","Omleiding: voor doorgaand verkeer","Omleiding: gemotoriseerd verkeer < 3,5 ton","Omleiding: gemotoriseerd verkeer > 3,5 ton","Omleiding: gemotoriseerd verkeer > 7,5 ton","Voetgangers hebben geen doorgang"]},"contactDetails":{"organisation":"nv De Scheepvaart","kboNumber":null,"lastName":"Sablon","firstName":"Stefan","phoneNumber1":"011298574","phoneNumber2":"0475559903","email":"stefan.sablon@vlaamsewaterweg.be","street":null,"number":null,"postalCode":null,"city":null,"country":"BE","extraAddressInfo":null},"diversions":[]}