{"state":"Concreet gepland","startDateTime":"2017-10-16T07:00:00","endDateTime":"2018-03-30T19:00:00","type":"Bouwen van een kunstwerk (brug, tunnel, kade, ...)","contractor":null,"mainContractor":null,"gipodId":1307019,"owner":"Gemeente Mol","reference":"Vernieuwe brug Weverstraat","description":"2400 Mol - Weversstraat - vernieuwen brug over Molse Nete - 20 m","comment":null,"location":{"cities":["Mol"],"coordinate":{"coordinates":[5.0782398009607963,51.172549563427488],"type":"Point","crs":{"type":"name","properties":{"name":"urn:ogc:def:crs:OGC:1.3:CRS84"}}},"geometry":{"coordinates":[[[5.0781596575203887,51.172607724470687],[5.0783914498861051,51.17257037482419],[5.078385002975689,51.17238164534681],[5.0781636955645331,51.172403201264572],[5.078168295564609,51.172470590839509],[5.0781596575203887,51.172607724470687]]],"type":"Polygon","crs":{"type":"name","properties":{"name":"urn:ogc:def:crs:OGC:1.3:CRS84"}}}},"url":null,"latestUpdate":"2017-08-28T12:05:49.353","hindrance":{"direction":null,"description":null,"locations":["Rijbaan"],"important":true,"effects":["Omleiding: beide richtingen","Afgesloten: volledige rijweg","Fietsers hebben geen doorgang","Voetgangers hebben geen doorgang"]},"contactDetails":{"organisation":"Gemeente Mol","kboNumber":null,"lastName":null,"firstName":null,"phoneNumber1":"014/330.711","phoneNumber2":null,"email":"info@gemeentemol.be","street":"Molenhoekstraat ","number":"2","postalCode":"2400","city":"Mol","country":"BE","extraAddressInfo":null},"diversions":[]}