{"state":"Concreet gepland","startDateTime":"2017-09-02T00:00:00","endDateTime":"2018-09-01T00:00:00","type":"Werken aan riolering","contractor":null,"mainContractor":null,"gipodId":1382706,"owner":"TMVW - Brugge-Kust","reference":"DOM-154/16/020-Z","description":"RIOLERINGSWERKEN - Oostende - 154-RL-Halvemaandijk (tss Vuurtorenweg e","comment":null,"location":{"cities":["Oostende"],"coordinate":{"coordinates":[2.9276879113037153,51.238420477202745],"type":"Point","crs":{"type":"name","properties":{"name":"urn:ogc:def:crs:OGC:1.3:CRS84"}}},"geometry":{"coordinates":[[[2.9291985112112888,51.237066844692926],[2.9291093829451693,51.237031145136939],[2.9283129271113695,51.238148019040743],[2.9279159394847247,51.238341436219144],[2.9275232253229579,51.238396443495006],[2.9275661858671467,51.238466197072256],[2.9279743225532928,51.238398790516307],[2.9283917442603209,51.238193034063904],[2.9291985112112888,51.237066844692926]]],"type":"Polygon","crs":{"type":"name","properties":{"name":"urn:ogc:def:crs:OGC:1.3:CRS84"}}}},"url":null,"latestUpdate":"2017-07-04T01:49:09.293","hindrance":{"direction":null,"description":null,"locations":["Voetpad","Fietspad","Parkeerstrook","Rijbaan"],"important":true,"effects":["Omleiding: beide richtingen","Afgesloten: volledige rijweg","Fietsers hebben geen doorgang","Handelaars bereikbaar","Plaatselijk verkeer: toegelaten","Voetgangers hebben doorgang"]},"contactDetails":{"organisation":"TMVW - Brugge-Kust","kboNumber":null,"lastName":"TMVW","firstName":null,"phoneNumber1":null,"phoneNumber2":null,"email":null,"street":null,"number":null,"postalCode":null,"city":null,"country":"BE","extraAddressInfo":null},"diversions":[]}