{"state":"In uitvoering","startDateTime":"2017-10-25T06:00:00","endDateTime":"2017-10-26T19:00:00","type":"Werken aan nutsleiding","contractor":"HARDO","mainContractor":{"organisation":"HARDO","lastName":null,"firstName":null},"gipodId":1827591,"owner":"Eandis Zenne-Dender","reference":"298112","description":"9420, ERPE-MERE, KLEINE STEENWEG: E en G Nieuw distributienet in verkaveling (69m)","comment":null,"location":{"cities":["Erpe-Mere"],"coordinate":{"coordinates":[3.9834595039438478,50.946800944466915],"type":"Point","crs":{"type":"name","properties":{"name":"urn:ogc:def:crs:OGC:1.3:CRS84"}}},"geometry":{"coordinates":[[[3.983458902314049,50.946796223079275],[3.9838172029526411,50.94669972546685],[3.9843144877569556,50.946500177018684],[3.984322109688871,50.946507770952984],[3.9838243394162873,50.946707515612182],[3.9838233121000424,50.946707853849823],[3.9834644695136712,50.94680449353735],[3.9834551400041485,50.946802116783921],[3.983458902314049,50.946796223079275]]],"type":"Polygon","crs":{"type":"name","properties":{"name":"urn:ogc:def:crs:OGC:1.3:CRS84"}}}},"url":"http://www.eandis.be","latestUpdate":"2017-10-26T03:01:58.63","hindrance":{"direction":null,"description":null,"locations":["Voetpad"],"important":false,"effects":["Fietsers hebben doorgang","Handelaars bereikbaar","Verminderde doorstroming in 1 richting","Voetgangers op de rijweg","Voetgangers hebben doorgang"]},"contactDetails":{"organisation":"Eandis Zenne-Dender","kboNumber":null,"lastName":null,"firstName":null,"phoneNumber1":"078/35.35.34","phoneNumber2":null,"email":"","street":"Industrielaan","number":"2","postalCode":"9320","city":"Aalst","country":"BE","extraAddressInfo":null},"diversions":[]}