{"state":"In uitvoering","startDateTime":"2017-02-20T08:00:00","endDateTime":"2017-11-22T17:00:00","type":"Werken aan nutsleiding","contractor":null,"mainContractor":null,"gipodId":1915133,"owner":"PIDPA drinkwater","reference":"D-21-031","description":"2380 RAVELS - Brouwersakker","comment":"","location":{"cities":["Ravels"],"coordinate":{"coordinates":[5.0175816635205273,51.413894677517085],"type":"Point","crs":{"type":"name","properties":{"name":"urn:ogc:def:crs:OGC:1.3:CRS84"}}},"geometry":{"coordinates":[[[5.01751719314844,51.41389595892872],[5.01759915300163,51.41391878951822],[5.0176286443931026,51.413869284075936],[5.0178868478108853,51.41346269225015],[5.01784503921169,51.413453663416149],[5.0176039429583925,51.4138399385725],[5.0175461750985315,51.413851130052286],[5.01751719314844,51.41389595892872]]],"type":"Polygon","crs":{"type":"name","properties":{"name":"urn:ogc:def:crs:OGC:1.3:CRS84"}}}},"url":null,"latestUpdate":"2017-08-22T12:45:47.037","hindrance":{"direction":" ","description":" ","locations":["Voetpad"],"important":false,"effects":["Fietsers hebben doorgang","Handelaars bereikbaar","Verminderde doorstroming in 1 richting","Voetgangers hebben doorgang"]},"contactDetails":{"organisation":"PIDPA drinkwater","kboNumber":null,"lastName":"synergie","firstName":null,"phoneNumber1":"080090300","phoneNumber2":null,"email":"synergie@pidpa.be","street":"Vierselse baan","number":"5","postalCode":"2280","city":"Grobbendonk","country":"BE","extraAddressInfo":null},"diversions":[]}