{"state":"In uitvoering","startDateTime":"2017-05-15T08:00:00","endDateTime":"2017-11-15T17:00:00","type":"Werken aan nutsleiding","contractor":null,"mainContractor":null,"gipodId":2021612,"owner":"PIDPA drinkwater","reference":"D-22-529","description":"2400 MOL - Gasstraat","comment":"","location":{"cities":["Mol"],"coordinate":{"coordinates":[5.1100667792099044,51.183979487466274],"type":"Point","crs":{"type":"name","properties":{"name":"urn:ogc:def:crs:OGC:1.3:CRS84"}}},"geometry":{"coordinates":[[[5.1097417240937,51.183586343831344],[5.1101839843151105,51.184190501264631],[5.1102746333006106,51.184161616570442],[5.1098266387370543,51.183565675425818],[5.1097417240937,51.183586343831344]]],"type":"Polygon","crs":{"type":"name","properties":{"name":"urn:ogc:def:crs:OGC:1.3:CRS84"}}}},"url":null,"latestUpdate":"2017-05-15T12:45:31.717","hindrance":{"direction":" ","description":" ","locations":["Voetpad"],"important":false,"effects":["Fietsers hebben doorgang","Handelaars bereikbaar","Verminderde doorstroming in 1 richting","Voetgangers hebben doorgang"]},"contactDetails":{"organisation":"PIDPA drinkwater","kboNumber":null,"lastName":"synergie","firstName":null,"phoneNumber1":"080090300","phoneNumber2":null,"email":"synergie@pidpa.be","street":"Vierselse baan","number":"5","postalCode":"2280","city":"Grobbendonk","country":"BE","extraAddressInfo":null},"diversions":[]}