{"state":"Concreet gepland","startDateTime":"2017-11-13T00:00:00","endDateTime":"2018-01-11T00:00:00","type":"Werken aan nutsleiding","contractor":null,"mainContractor":null,"gipodId":2084166,"owner":"TMVW - Centraal","reference":"DOM-262/17/000-D","description":"WERKEN AAN DRINKWATERDISTRIBUTIELEIDINGEN - Zelzate - 262-AL Hoogbouwplein Zelzate","comment":null,"location":{"cities":["Zelzate"],"coordinate":{"coordinates":[3.7925998626754525,51.19635599264268],"type":"Point","crs":{"type":"name","properties":{"name":"urn:ogc:def:crs:OGC:1.3:CRS84"}}},"geometry":{"coordinates":[[[3.7925590657856221,51.1963284265466],[3.7926413154385759,51.195938077417829],[3.7927138494651249,51.195942991472926],[3.7927262487890347,51.195918724704526],[3.7926512943616126,51.195913798871409],[3.792707226786713,51.195695129666206],[3.7927822183527318,51.195697015653366],[3.7927800618228864,51.19567571890925],[3.7926711005951423,51.195681270205291],[3.7925299350885027,51.196335886457831],[3.7926358773227151,51.196378974849971],[3.7926337756609132,51.196353116589009],[3.7925590657856221,51.1963284265466]]],"type":"Polygon","crs":{"type":"name","properties":{"name":"urn:ogc:def:crs:OGC:1.3:CRS84"}}}},"url":null,"latestUpdate":"2017-09-24T02:46:14.247","hindrance":{"direction":null,"description":null,"locations":["Voetpad"],"important":false,"effects":["Fietsers hebben doorgang","Handelaars bereikbaar","Verminderde doorstroming in 1 richting","Voetgangers hebben doorgang"]},"contactDetails":{"organisation":"TMVW - Centraal","kboNumber":null,"lastName":"TMVW","firstName":null,"phoneNumber1":null,"phoneNumber2":null,"email":null,"street":null,"number":null,"postalCode":null,"city":null,"country":"BE","extraAddressInfo":null},"diversions":[]}