{"state":"Concreet gepland","startDateTime":"2017-10-23T00:00:00","endDateTime":"2017-10-25T00:00:00","type":"Werken aan nutsleiding","contractor":null,"mainContractor":null,"gipodId":2383508,"owner":"Infrax Site Hasselt","reference":"P/042808","description":"3960 BREE Itterplein Gas Elektriciteit Kabeltelevisie 100 M Uitbreiding","comment":"Zijde van de straat: Paar","location":{"cities":["Bree"],"coordinate":{"coordinates":[5.64698945506918,51.116435690663394],"type":"Point","crs":{"type":"name","properties":{"name":"urn:ogc:def:crs:OGC:1.3:CRS84"}}},"geometry":{"coordinates":[[[5.6474523077837366,51.116174109737059],[5.6473924882281592,51.116146421821909],[5.6472358572117622,51.116271122657132],[5.6471027468563282,51.11636021927167],[5.6467275473192737,51.1161366673878],[5.6466669729806593,51.116177950132538],[5.6470422568044052,51.11638892418182],[5.6469391261889825,51.116445645934043],[5.64698698214863,51.116472501851078],[5.6474523077837366,51.116174109737059]]],"type":"Polygon","crs":{"type":"name","properties":{"name":"urn:ogc:def:crs:OGC:1.3:CRS84"}}}},"url":null,"latestUpdate":"2017-10-20T14:25:16.727","hindrance":{"direction":null,"description":null,"locations":["Voetpad","Parkeerstrook","Zijberm"],"important":false,"effects":["Afgesloten: 1 rijstrook"]},"contactDetails":{"organisation":"Infrax Site Hasselt","kboNumber":null,"lastName":null,"firstName":null,"phoneNumber1":null,"phoneNumber2":null,"email":"netaanleg.oost@infrax.be","street":"Trichterheideweg","number":"8","postalCode":"3500","city":"Hasselt","country":"BE","extraAddressInfo":null},"diversions":[]}