{"state":"Concreet gepland","startDateTime":"2017-11-22T00:00:00","endDateTime":"2017-11-23T00:00:00","type":"Werken aan nutsleiding","contractor":null,"mainContractor":null,"gipodId":2493927,"owner":"Infrax Site Hasselt","reference":"P/043295","description":"   Openbare verlichting 30 M Uitbreiding","comment":null,"location":{"cities":["Hasselt"],"coordinate":{"coordinates":[5.3556039323164892,50.93479665029934],"type":"Point","crs":{"type":"name","properties":{"name":"urn:ogc:def:crs:OGC:1.3:CRS84"}}},"geometry":{"coordinates":[[[5.3553968837881829,50.934829358092671],[5.3560373323436519,50.934812863022366],[5.35599377654827,50.934717305128423],[5.3553775810590718,50.934747728582742],[5.3553968837881829,50.934829358092671]]],"type":"Polygon","crs":{"type":"name","properties":{"name":"urn:ogc:def:crs:OGC:1.3:CRS84"}}}},"url":null,"latestUpdate":"2017-10-27T09:37:48.64","hindrance":{"direction":null,"description":null,"locations":["Voetpad","Parkeerstrook","Zijberm"],"important":false,"effects":["Afgesloten: 1 rijstrook"]},"contactDetails":{"organisation":"Infrax Site Hasselt","kboNumber":null,"lastName":null,"firstName":null,"phoneNumber1":null,"phoneNumber2":null,"email":"netaanleg.oost@infrax.be","street":"Trichterheideweg","number":"8","postalCode":"3500","city":"Hasselt","country":"BE","extraAddressInfo":null},"diversions":[]}